gqylpy_dict/__init__.py
gqylpy_dict/g dict.py
gqylpy_dict-1.2.6.dist-info/LICENSE
gqylpy_dict-1.2.6.dist-info/METADATA
gqylpy_dict-1.2.6.dist-info/NOTICE
gqylpy_dict-1.2.6.dist-info/WHEEL
gqylpy_dict-1.2.6.dist-info/top_level.txt
gqylpy_dict-1.2.6.dist-info/RECORD
